{
  "global_groups": {
    "neophyten_stmk_gesetz": {
      "name": "Invasive Neophyten (Unionsliste - Absolutes Verbot)",
      "plants": [
        "Ailanthus altissima (Götterbaum)",
        "Heracleum mantegazzianum (Riesenbärenklau)",
        "Reynoutria japonica (Japanischer Staudenknöterich)",
        "Impatiens glandulifera (Drüsiges Springkraut)",
        "Ambrosia artemisiifolia (Aufrechte Ambrosia)",
        "Asclepias syriaca (Gewöhnliche Seidenpflanze)"
      ],
      "grund": "Absolutes Verbot gemäß EU-Verordnung 1143/2014 zum Schutz der heimischen Biodiversität und Gesundheit.",
      "quelle": "Steiermärkisches IAS-Gesetz & EU-Verbotsliste"
    },
    "feuerbrand_wirtspflanzen_kernliste": {
      "name": "Feuerbrand-Hauptwirtspflanzen (Striktes Verbot)",
      "plants": [
        "Cotoneaster (alle Arten der Zwergmispel)",
        "Crataegus (Weißdorn und Rotdorn)",
        "Pyracantha (Feuerdorn)",
        "Photinia davidiana (Lorbeermispel - ehem. Stranvaesia)",
        "Eriobotrya (Wollmispel)"
      ],
      "grund": "Präventivschutz des Erwerbsobstbaus vor Erwinia amylovora. Andere ehem. Wirtspflanzen sind seit 2021/2022 wieder zulässig.",
      "quelle": "Steiermärkische Feuerbrandverordnung (Fassung 2026)"
    },
    "bebauungsplan_standard_stmk": {
      "name": "Standard-Bebauungsplan (Ortsbild & Ökologie)",
      "plants": [
        "Thuja (alle Arten des Lebensbaums)",
        "Prunus laurocerasus (Kirschlorbeer)",
        "Chamaecyparis (Scheinzypresse)",
        "Picea pungens (Blaufichte)",
        "Schottervorgärten / Kiesflächen (großflächig)",
        "Abies concolor (Kolorado-Tanne)"
      ],
      "grund": "Vermeidung von Hitzeinseln und Erhalt des Landschaftsbildes.",
      "quelle": "Steiermärkisches Baugesetz & Lokale Bebauungspläne"
    }
  },
  "municipalities": {
    "Graz": {
      "groups": ["neophyten_stmk_gesetz", "bebauungsplan_standard_stmk"],
      "custom_rules": {
        "kugelfoermige_gehoelze": { "status": "teilweise verboten", "grund": "Untersagung künstlicher Wuchsformen in Kerngebieten.", "quelle": "Stadt Graz, Stadtplanungsamt" },
        "einfriedungen": { "status": "beschränkt", "grund": "Heckenhöhe max. 1,50m bis 2,00m; Verbot blickdichter Kunststoffzäune.", "quelle": "Grazer Bebauungsplan-Leitfaden" }
      }
    },
    "Kainbach bei Graz": { "groups": ["neophyten_stmk_gesetz", "feuerbrand_wirtspflanzen_kernliste", "bebauungsplan_standard_stmk"] },
    "Hart bei Graz": { "groups": ["neophyten_stmk_gesetz", "feuerbrand_wirtspflanzen_kernliste", "bebauungsplan_standard_stmk"] },
    "Thal": { "groups": ["neophyten_stmk_gesetz", "bebauungsplan_standard_stmk"], "custom_rules": { "thuja": { "status": "verboten", "grund": "Erhaltung des naturnahen Charakters.", "quelle": "Marktgemeinde Thal" } } },
    "Haselsdorf-Tobelbad": { "groups": ["neophyten_stmk_gesetz", "feuerbrand_wirtspflanzen_kernliste"] },
    "Seiersberg-Pirka": { "groups": ["neophyten_stmk_gesetz", "bebauungsplan_standard_stmk"] },
    "St. Radegund bei Graz": { "groups": ["neophyten_stmk_gesetz"] },
    "Kumberg": { "groups": ["neophyten_stmk_gesetz", "feuerbrand_wirtspflanzen_kernliste"] },
    "Eggersdorf bei Graz": { "groups": ["neophyten_stmk_gesetz", "feuerbrand_wirtspflanzen_kernliste"] },
    "Hausmannstätten": { "groups": ["neophyten_stmk_gesetz", "bebauungsplan_standard_stmk"] },
    "Fernitz-Mellach": { "groups": ["neophyten_stmk_gesetz", "bebauungsplan_standard_stmk"] },
    "Feldkirchen bei Graz": { "groups": ["neophyten_stmk_gesetz", "bebauungsplan_standard_stmk"] },
    "Raaba-Grambach": { "groups": ["neophyten_stmk_gesetz", "feuerbrand_wirtspflanzen_kernliste", "bebauungsplan_standard_stmk"] },
    "Vasoldsberg": { "groups": ["neophyten_stmk_gesetz", "feuerbrand_wirtspflanzen_kernliste"] },
    "Gratkorn": { "groups": ["neophyten_stmk_gesetz", "bebauungsplan_standard_stmk"] },
    "Semriach": { "groups": ["neophyten_stmk_gesetz"] },
    "Gratwein-Straßengel": { "groups": ["neophyten_stmk_gesetz", "bebauungsplan_standard_stmk"], "custom_rules": { "wallfahrtskirche": { "status": "verboten", "grund": "Ortsbildschutz im Sichtfeld der Kirche.", "quelle": "Marktgemeinde Gratwein-Straßengel" } } },
    "St. Oswald bei Plankenwarth": { "groups": ["neophyten_stmk_gesetz"] },
    "Peggau": { "groups": ["neophyten_stmk_gesetz", "bebauungsplan_standard_stmk"] },
    "Deutschfeistritz": { "groups": ["neophyten_stmk_gesetz", "bebauungsplan_standard_stmk"] },
    "Übelbach": { "groups": ["neophyten_stmk_gesetz"] },
    "Frohnleiten": { "groups": ["neophyten_stmk_gesetz", "bebauungsplan_standard_stmk"] },
    "Premstätten": { "groups": ["neophyten_stmk_gesetz", "bebauungsplan_standard_stmk"] },
    "Wundschuh": { "groups": ["neophyten_stmk_gesetz", "feuerbrand_wirtspflanzen_kernliste"] },
    "Dobl-Zwaring": { "groups": ["neophyten_stmk_gesetz", "feuerbrand_wirtspflanzen_kernliste", "bebauungsplan_standard_stmk"] },
    "Hitzendorf": { "groups": ["neophyten_stmk_gesetz", "feuerbrand_wirtspflanzen_kernliste", "bebauungsplan_standard_stmk"] },
    "Stallhofen": { "groups": ["neophyten_stmk_gesetz", "feuerbrand_wirtspflanzen_kernliste"] },
    "Lassnitzhöhe": { "groups": ["neophyten_stmk_gesetz", "bebauungsplan_standard_stmk"] },
    "Nestelbach bei Graz": { "groups": ["neophyten_stmk_gesetz", "feuerbrand_wirtspflanzen_kernliste"] },
    "St. Marein bei Graz": { "groups": ["neophyten_stmk_gesetz", "feuerbrand_wirtspflanzen_kernliste"] },
    "Bruck an der Mur": { "groups": ["neophyten_stmk_gesetz", "bebauungsplan_standard_stmk"] },
    "Kapfenberg": { "groups": ["neophyten_stmk_gesetz", "bebauungsplan_standard_stmk"] },
    "Tragöß-St. Katharein": { "groups": ["neophyten_stmk_gesetz"] },
    "Aflenz": { "groups": ["neophyten_stmk_gesetz"] },
    "Turnau": { "groups": ["neophyten_stmk_gesetz"] },
    "Mariazell": { "groups": ["neophyten_stmk_gesetz", "bebauungsplan_standard_stmk"] },
    "St. Marein im Mürztal": { "groups": ["neophyten_stmk_gesetz", "bebauungsplan_standard_stmk"] },
    "St. Lorenzen im Mürztal": { "groups": ["neophyten_stmk_gesetz", "bebauungsplan_standard_stmk"] },
    "Kindberg": { "groups": ["neophyten_stmk_gesetz", "bebauungsplan_standard_stmk"] },
    "Stanz im Mürztal": { "groups": ["neophyten_stmk_gesetz"] },
    "Fischbach": { "groups": ["neophyten_stmk_gesetz"] },
    "Sankt Barbara im Mürztal": { "groups": ["neophyten_stmk_gesetz", "bebauungsplan_standard_stmk"] },
    "Langenwang": { "groups": ["neophyten_stmk_gesetz", "bebauungsplan_standard_stmk"] },
    "Krieglach": { "groups": ["neophyten_stmk_gesetz", "bebauungsplan_standard_stmk"] },
    "Ratten": { "groups": ["neophyten_stmk_gesetz"] },
    "Mürzzuschlag": { "groups": ["neophyten_stmk_gesetz", "bebauungsplan_standard_stmk"] },
    "Spital am Semmering": { "groups": ["neophyten_stmk_gesetz"] },
    "Neuberg an der Mürz": { "groups": ["neophyten_stmk_gesetz"] },
    "Lieboch": { "groups": ["neophyten_stmk_gesetz", "bebauungsplan_standard_stmk"] },
    "Lannach": { "groups": ["neophyten_stmk_gesetz", "bebauungsplan_standard_stmk"] },
    "St. Josef (Weststeiermark)": { "groups": ["neophyten_stmk_gesetz", "feuerbrand_wirtspflanzen_kernliste"] },
    "Preding": { "groups": ["neophyten_stmk_gesetz", "feuerbrand_wirtspflanzen_kernliste"] },
    "St. Nikolai im Sausal": { "groups": ["neophyten_stmk_gesetz", "feuerbrand_wirtspflanzen_kernliste", "bebauungsplan_standard_stmk"] },
    "Stainz": { "groups": ["neophyten_stmk_gesetz", "feuerbrand_wirtspflanzen_kernliste", "bebauungsplan_standard_stmk"] },
    "Sankt Stefan ob Stainz": { "groups": ["neophyten_stmk_gesetz", "feuerbrand_wirtspflanzen_kernliste"] },
    "Wettmannstätten": { "groups": ["neophyten_stmk_gesetz", "feuerbrand_wirtspflanzen_kernliste"] },
    "Groß St. Florian": { "groups": ["neophyten_stmk_gesetz", "bebauungsplan_standard_stmk"] },
    "Frauental an der Laßnitz": { "groups": ["neophyten_stmk_gesetz", "bebauungsplan_standard_stmk"] },
    "Bad Gams": { "groups": ["neophyten_stmk_gesetz", "bebauungsplan_standard_stmk"] },
    "Deutschlandsberg": { "groups": ["neophyten_stmk_gesetz", "bebauungsplan_standard_stmk"] },
    "Schwanberg": { "groups": ["neophyten_stmk_gesetz", "bebauungsplan_standard_stmk"] },
    "St. Peter im Sulmtal": { "groups": ["neophyten_stmk_gesetz", "feuerbrand_wirtspflanzen_kernliste"] },
    "St. Martin im Sulmtal": { "groups": ["neophyten_stmk_gesetz", "feuerbrand_wirtspflanzen_kernliste"] },
    "Pölfing-Brunn": { "groups": ["neophyten_stmk_gesetz"] },
    "Wies": { "groups": ["neophyten_stmk_gesetz", "bebauungsplan_standard_stmk"] },
    "Eibiswald": { "groups": ["neophyten_stmk_gesetz"] },
    "Söding-Sankt Johann": { "groups": ["neophyten_stmk_gesetz", "bebauungsplan_standard_stmk"] },
    "Hartberg": { "groups": ["neophyten_stmk_gesetz", "feuerbrand_wirtspflanzen_kernliste", "bebauungsplan_standard_stmk"] },
    "St. Johann in der Haide": { "groups": ["neophyten_stmk_gesetz", "feuerbrand_wirtspflanzen_kernliste", "bebauungsplan_standard_stmk"] },
    "Stubenberg": { "groups": ["neophyten_stmk_gesetz", "feuerbrand_wirtspflanzen_kernliste"] },
    "Kaindorf": { "groups": ["neophyten_stmk_gesetz", "feuerbrand_wirtspflanzen_kernliste", "bebauungsplan_standard_stmk"] },
    "Pöllau": { "groups": ["neophyten_stmk_gesetz", "feuerbrand_wirtspflanzen_kernliste"] },
    "Grafendorf bei Hartberg": { "groups": ["neophyten_stmk_gesetz", "feuerbrand_wirtspflanzen_kernliste"] },
    "Lafnitz": { "groups": ["neophyten_stmk_gesetz", "feuerbrand_wirtspflanzen_kernliste"] },
    "Friedberg": { "groups": ["neophyten_stmk_gesetz", "bebauungsplan_standard_stmk"] },
    "Pinggau": { "groups": ["neophyten_stmk_gesetz", "bebauungsplan_standard_stmk"] },
    "Ilz": { "groups": ["neophyten_stmk_gesetz", "feuerbrand_wirtspflanzen_kernliste", "bebauungsplan_standard_stmk"] },
    "Großwilfersdorf": { "groups": ["neophyten_stmk_gesetz", "feuerbrand_wirtspflanzen_kernliste"] },
    "Bad Waltersdorf": { "groups": ["neophyten_stmk_gesetz", "feuerbrand_wirtspflanzen_kernliste", "bebauungsplan_standard_stmk"] },
    "Fürstenfeld": { "groups": ["neophyten_stmk_gesetz", "feuerbrand_wirtspflanzen_kernliste", "bebauungsplan_standard_stmk"] },
    "Bad Blumau": { "groups": ["neophyten_stmk_gesetz", "bebauungsplan_standard_stmk"] },
    "Burgau": { "groups": ["neophyten_stmk_gesetz", "feuerbrand_wirtspflanzen_kernliste"] },
    "Neudau": { "groups": ["neophyten_stmk_gesetz", "bebauungsplan_standard_stmk"] },
    "Markt Hartmannsdorf": { "groups": ["neophyten_stmk_gesetz", "feuerbrand_wirtspflanzen_kernliste"] },
    "Kalsdorf bei Graz": { "groups": ["neophyten_stmk_gesetz", "bebauungsplan_standard_stmk"] },
    "Werndorf": { "groups": ["neophyten_stmk_gesetz", "bebauungsplan_standard_stmk"] },
    "Wildon": { "groups": ["neophyten_stmk_gesetz", "bebauungsplan_standard_stmk"] },
    "Hengsberg": { "groups": ["neophyten_stmk_gesetz", "feuerbrand_wirtspflanzen_kernliste"] },
    "Allerheiligen bei Wildon": { "groups": ["neophyten_stmk_gesetz", "feuerbrand_wirtspflanzen_kernliste"] },
    "Sankt Georgen an der Stiefing": { "groups": ["neophyten_stmk_gesetz", "feuerbrand_wirtspflanzen_kernliste", "bebauungsplan_standard_stmk"] },
    "Wolfsberg im Schwarzautal": { "groups": ["neophyten_stmk_gesetz", "feuerbrand_wirtspflanzen_kernliste"] },
    "Sankt Veit am Vogau": { "groups": ["neophyten_stmk_gesetz", "feuerbrand_wirtspflanzen_kernliste"] },
    "Gabersdorf": { "groups": ["neophyten_stmk_gesetz", "bebauungsplan_standard_stmk"] },
    "Leibnitz": { "groups": ["neophyten_stmk_gesetz", "bebauungsplan_standard_stmk"] },
    "Gralla": { "groups": ["neophyten_stmk_gesetz", "bebauungsplan_standard_stmk"] },
    "Tillmitsch": { "groups": ["neophyten_stmk_gesetz", "bebauungsplan_standard_stmk"] },
    "Wagna": { "groups": ["neophyten_stmk_gesetz", "bebauungsplan_standard_stmk"] },
    "Kitzeck im Sausal": { "groups": ["neophyten_stmk_gesetz", "bebauungsplan_standard_stmk"] },
    "Gleinstätten": { "groups": ["neophyten_stmk_gesetz", "feuerbrand_wirtspflanzen_kernliste", "bebauungsplan_standard_stmk"] },
    "Heimschuh": { "groups": ["neophyten_stmk_gesetz", "feuerbrand_wirtspflanzen_kernliste"] },
    "Großklein": { "groups": ["neophyten_stmk_gesetz", "bebauungsplan_standard_stmk"] },
    "Arnfels": { "groups": ["neophyten_stmk_gesetz"] },
    "Ehrenhausen an der Weinstraße": { "groups": ["neophyten_stmk_gesetz", "bebauungsplan_standard_stmk"] },
    "Gamlitz": { "groups": ["neophyten_stmk_gesetz", "bebauungsplan_standard_stmk"] },
    "Leutschach an der Weinstraße": { "groups": ["neophyten_stmk_gesetz", "bebauungsplan_standard_stmk"] },
    "Straß in Steiermark": { "groups": ["neophyten_stmk_gesetz", "bebauungsplan_standard_stmk"] },
    "Mureck": { "groups": ["neophyten_stmk_gesetz", "bebauungsplan_standard_stmk"] },
    "Leoben": { "groups": ["neophyten_stmk_gesetz", "bebauungsplan_standard_stmk"] },
    "Niklasdorf": { "groups": ["neophyten_stmk_gesetz", "bebauungsplan_standard_stmk"] },
    "St. Stefan ob Leoben": { "groups": ["neophyten_stmk_gesetz", "bebauungsplan_standard_stmk"] },
    "Kraubath an der Mur": { "groups": ["neophyten_stmk_gesetz"] },
    "Sankt Michael in Obersteiermark": { "groups": ["neophyten_stmk_gesetz", "bebauungsplan_standard_stmk"] },
    "Traboch (Timmersdorf)": { "groups": ["neophyten_stmk_gesetz", "bebauungsplan_standard_stmk"] },
    "Kammern im Liesingtal": { "groups": ["neophyten_stmk_gesetz"] },
    "Mautern in Steiermark": { "groups": ["neophyten_stmk_gesetz"] },
    "Kalwang": { "groups": ["neophyten_stmk_gesetz"] },
    "Wald am Schoberpaß": { "groups": ["neophyten_stmk_gesetz"] },
    "Eisenerz": { "groups": ["neophyten_stmk_gesetz"] },
    "St. Peter-Freienstein": { "groups": ["neophyten_stmk_gesetz", "bebauungsplan_standard_stmk"] },
    "Trofaiach": { "groups": ["neophyten_stmk_gesetz", "bebauungsplan_standard_stmk"] },
    "Vordernberg": { "groups": ["neophyten_stmk_gesetz"] },
    "Radmer": { "groups": ["neophyten_stmk_gesetz"] },
    "Selzthal": { "groups": ["neophyten_stmk_gesetz", "bebauungsplan_standard_stmk"] },
    "Lassing": { "groups": ["neophyten_stmk_gesetz"] },
    "Ardning": { "groups": ["neophyten_stmk_gesetz"] },
    "Admont": { "groups": ["neophyten_stmk_gesetz", "bebauungsplan_standard_stmk"] },
    "Weißenbach an der Enns": { "groups": ["neophyten_stmk_gesetz"] },
    "Weng im Gesäuse": { "groups": ["neophyten_stmk_gesetz"] },
    "Hall bei Admont": { "groups": ["neophyten_stmk_gesetz"] },
    "Hieflau": { "groups": ["neophyten_stmk_gesetz"] },
    "Altenmarkt bei Sankt Gallen": { "groups": ["neophyten_stmk_gesetz", "bebauungsplan_standard_stmk"] },
    "Landl": { "groups": ["neophyten_stmk_gesetz"] },
    "Wildalpen": { "groups": ["neophyten_stmk_gesetz"] },
    "Sankt Gallen": { "groups": ["neophyten_stmk_gesetz", "bebauungsplan_standard_stmk"] },
    "Liezen": { "groups": ["neophyten_stmk_gesetz", "bebauungsplan_standard_stmk"] },
    "Wörschach": { "groups": ["neophyten_stmk_gesetz", "bebauungsplan_standard_stmk"] },
    "Aigen im Ennstal": { "groups": ["neophyten_stmk_gesetz", "bebauungsplan_standard_stmk"] },
    "Stainach-Pürgg": { "groups": ["neophyten_stmk_gesetz", "bebauungsplan_standard_stmk"] },
    "Irdning-Donnersbachtal": { "groups": ["neophyten_stmk_gesetz", "bebauungsplan_standard_stmk"] },
    "St. Martin am Grimming": { "groups": ["neophyten_stmk_gesetz", "bebauungsplan_standard_stmk"] },
    "Öblarn": { "groups": ["neophyten_stmk_gesetz"] },
    "Stein an der Enns": { "groups": ["neophyten_stmk_gesetz"] },
    "Gröbming": { "groups": ["neophyten_stmk_gesetz", "bebauungsplan_standard_stmk"] },
    "Haus im Ennstal": { "groups": ["neophyten_stmk_gesetz", "bebauungsplan_standard_stmk"] },
    "Aich": { "groups": ["neophyten_stmk_gesetz", "bebauungsplan_standard_stmk"] },
    "Schladming": { "groups": ["neophyten_stmk_gesetz", "bebauungsplan_standard_stmk"] },
    "Ramsau am Dachstein": { "groups": ["neophyten_stmk_gesetz"] },
    "Bad Mitterndorf": { "groups": ["neophyten_stmk_gesetz", "bebauungsplan_standard_stmk"] },
    "Bad Aussee": { "groups": ["neophyten_stmk_gesetz", "bebauungsplan_standard_stmk"] },
    "Altaussee": { "groups": ["neophyten_stmk_gesetz", "bebauungsplan_standard_stmk"] },
    "Grundlsee": { "groups": ["neophyten_stmk_gesetz", "bebauungsplan_standard_stmk"] },
    "Murau": { "groups": ["neophyten_stmk_gesetz", "bebauungsplan_standard_stmk"] },
    "St. Lambrecht": { "groups": ["neophyten_stmk_gesetz"] },
    "Neumarkt in der Steiermark": { "groups": ["neophyten_stmk_gesetz", "bebauungsplan_standard_stmk"] },
    "Scheifling": { "groups": ["neophyten_stmk_gesetz", "bebauungsplan_standard_stmk"] },
    "Teufenbach-Katsch": { "groups": ["neophyten_stmk_gesetz", "bebauungsplan_standard_stmk"] },
    "Oberwölz": { "groups": ["neophyten_stmk_gesetz"] },
    "Niederwölz": { "groups": ["neophyten_stmk_gesetz"] },
    "Ranten": { "groups": ["neophyten_stmk_gesetz"] },
    "Krakau": { "groups": ["neophyten_stmk_gesetz"] },
    "Stadl-Predlitz": { "groups": ["neophyten_stmk_gesetz"] },
    "St. Georgen am Kreischberg": { "groups": ["neophyten_stmk_gesetz", "bebauungsplan_standard_stmk"] },
    "Mühlen": { "groups": ["neophyten_stmk_gesetz"] },
    "St. Peter am Kammersberg": { "groups": ["neophyten_stmk_gesetz", "bebauungsplan_standard_stmk"] },
    "Judenburg": { "groups": ["neophyten_stmk_gesetz", "bebauungsplan_standard_stmk"] },
    "Knittelfeld": { "groups": ["neophyten_stmk_gesetz", "bebauungsplan_standard_stmk"] },
    "Spielberg": { "groups": ["neophyten_stmk_gesetz", "bebauungsplan_standard_stmk"] },
    "Zeltweg": { "groups": ["neophyten_stmk_gesetz", "bebauungsplan_standard_stmk"] },
    "Pöls-Oberkurzheim": { "groups": ["neophyten_stmk_gesetz", "bebauungsplan_standard_stmk"] },
    "Fohnsdorf": { "groups": ["neophyten_stmk_gesetz", "bebauungsplan_standard_stmk"] },
    "Obdach": { "groups": ["neophyten_stmk_gesetz"] },
    "Weißkirchen in Steiermark": { "groups": ["neophyten_stmk_gesetz", "feuerbrand_wirtspflanzen_kernliste"] },
    "Pölstal": { "groups": ["neophyten_stmk_gesetz"] },
    "Hohentauern": { "groups": ["neophyten_stmk_gesetz"] },
    "Gaal": { "groups": ["neophyten_stmk_gesetz"] },
    "Seckau": { "groups": ["neophyten_stmk_gesetz"] },
    "St. Marein-Feistritz": { "groups": ["neophyten_stmk_gesetz", "bebauungsplan_standard_stmk"] },
    "St. Margarethen bei Knittelfeld": { "groups": ["neophyten_stmk_gesetz", "bebauungsplan_standard_stmk"] },
    "Feldbach": { "groups": ["neophyten_stmk_gesetz", "feuerbrand_wirtspflanzen_kernliste", "bebauungsplan_standard_stmk"] },
    "Bad Gleichenberg": { "groups": ["neophyten_stmk_gesetz", "bebauungsplan_standard_stmk"] },
    "Bad Radkersburg": { "groups": ["neophyten_stmk_gesetz", "bebauungsplan_standard_stmk"] },
    "Fehring": { "groups": ["neophyten_stmk_gesetz", "feuerbrand_wirtspflanzen_kernliste", "bebauungsplan_standard_stmk"] },
    "Gnas": { "groups": ["neophyten_stmk_gesetz", "feuerbrand_wirtspflanzen_kernliste"] },
    "Straden": { "groups": ["neophyten_stmk_gesetz", "feuerbrand_wirtspflanzen_kernliste"] },
    "Riegersburg": { "groups": ["neophyten_stmk_gesetz", "feuerbrand_wirtspflanzen_kernliste"] },
    "Kirchberg an der Raab": { "groups": ["neophyten_stmk_gesetz", "feuerbrand_wirtspflanzen_kernliste", "bebauungsplan_standard_stmk"] },
    "St. Stefan im Rosental": { "groups": ["neophyten_stmk_gesetz", "feuerbrand_wirtspflanzen_kernliste"] },
    "Paldau": { "groups": ["neophyten_stmk_gesetz", "feuerbrand_wirtspflanzen_kernliste"] },
    "Kirchbach-Zerlach": { "groups": ["neophyten_stmk_gesetz", "feuerbrand_wirtspflanzen_kernliste"] },
    "Jagerberg": { "groups": ["neophyten_stmk_gesetz", "feuerbrand_wirtspflanzen_kernliste"] },
    "Mettersdorf am Saßbach": { "groups": ["neophyten_stmk_gesetz", "feuerbrand_wirtspflanzen_kernliste"] },
    "Sankt Peter am Ottersbach": { "groups": ["neophyten_stmk_gesetz", "feuerbrand_wirtspflanzen_kernliste"] },
    "Halbenrain": { "groups": ["neophyten_stmk_gesetz", "bebauungsplan_standard_stmk"] },
    "Klöch": { "groups": ["neophyten_stmk_gesetz", "bebauungsplan_standard_stmk"] },
    "Tieschen": { "groups": ["neophyten_stmk_gesetz", "feuerbrand_wirtspflanzen_kernliste"] },
    "Kapfenstein": { "groups": ["neophyten_stmk_gesetz", "feuerbrand_wirtspflanzen_kernliste"] },
    "Edelsbach bei Feldbach": { "groups": ["neophyten_stmk_gesetz", "feuerbrand_wirtspflanzen_kernliste"] },
    "Eichkögl": { "groups": ["neophyten_stmk_gesetz", "feuerbrand_wirtspflanzen_kernliste"] },
    "Voitsberg": { "groups": ["neophyten_stmk_gesetz", "bebauungsplan_standard_stmk"] },
    "Bärnbach": { "groups": ["neophyten_stmk_gesetz", "bebauungsplan_standard_stmk"] },
    "Köflach": { "groups": ["neophyten_stmk_gesetz", "bebauungsplan_standard_stmk"] },
    "Maria Lankowitz": { "groups": ["neophyten_stmk_gesetz", "bebauungsplan_standard_stmk"] },
    "Edelschrott": { "groups": ["neophyten_stmk_gesetz"] },
    "Hirschegg-Pack": { "groups": ["neophyten_stmk_gesetz"] },
    "Kainach bei Voitsberg": { "groups": ["neophyten_stmk_gesetz"] },
    "Krottendorf-Gaisfeld": { "groups": ["neophyten_stmk_gesetz", "bebauungsplan_standard_stmk"] },
    "Ligist": { "groups": ["neophyten_stmk_gesetz", "feuerbrand_wirtspflanzen_kernliste"] },
    "Mooskirchen": { "groups": ["neophyten_stmk_gesetz", "feuerbrand_wirtspflanzen_kernliste", "bebauungsplan_standard_stmk"] },
    "Rosental an der Kainach": { "groups": ["neophyten_stmk_gesetz", "bebauungsplan_standard_stmk"] },
    "Sankt Martin am Wöllmißberg": { "groups": ["neophyten_stmk_gesetz"] },
    "Weiz": { "groups": ["neophyten_stmk_gesetz", "feuerbrand_wirtspflanzen_kernliste", "bebauungsplan_standard_stmk"] },
    "Gleisdorf": { "groups": ["neophyten_stmk_gesetz", "feuerbrand_wirtspflanzen_kernliste", "bebauungsplan_standard_stmk"] },
    "Puch bei Weiz": { "groups": ["neophyten_stmk_gesetz", "feuerbrand_wirtspflanzen_kernliste"] },
    "St. Ruprecht an der Raab": { "groups": ["neophyten_stmk_gesetz", "feuerbrand_wirtspflanzen_kernliste", "bebauungsplan_standard_stmk"] },
    "Anger": { "groups": ["neophyten_stmk_gesetz", "feuerbrand_wirtspflanzen_kernliste"] },
    "Birkfeld": { "groups": ["neophyten_stmk_gesetz", "bebauungsplan_standard_stmk"] },
    "Passail": { "groups": ["neophyten_stmk_gesetz"] },
    "St. Margarethen an der Raab": { "groups": ["neophyten_stmk_gesetz", "feuerbrand_wirtspflanzen_kernliste", "bebauungsplan_standard_stmk"] },
    "Pischelsdorf am Kulm": { "groups": ["neophyten_stmk_gesetz", "feuerbrand_wirtspflanzen_kernliste"] },
    "Sinabelkirchen": { "groups": ["neophyten_stmk_gesetz", "feuerbrand_wirtspflanzen_kernliste", "bebauungsplan_standard_stmk"] },
    "Floing": { "groups": ["neophyten_stmk_gesetz", "feuerbrand_wirtspflanzen_kernliste"] },
    "Mortantsch": { "groups": ["neophyten_stmk_gesetz", "feuerbrand_wirtspflanzen_kernliste", "bebauungsplan_standard_stmk"] },
    "Naas": { "groups": ["neophyten_stmk_gesetz", "feuerbrand_wirtspflanzen_kernliste"] },
    "Thannhausen": { "groups": ["neophyten_stmk_gesetz", "feuerbrand_wirtspflanzen_kernliste"] },
    "Gutenberg-Stenzengreith": { "groups": ["neophyten_stmk_gesetz", "feuerbrand_wirtspflanzen_kernliste"] },
    "St. Kathrein am Offenegg": { "groups": ["neophyten_stmk_gesetz"] },
    "Gasen": { "groups": ["neophyten_stmk_gesetz"] },
    "Rettenegg": { "groups": ["neophyten_stmk_gesetz"] },
    "Strallegg": { "groups": ["neophyten_stmk_gesetz"] },
    "Miesenbach bei Birkfeld": { "groups": ["neophyten_stmk_gesetz"] },
    "Ludmannsdorf": { "groups": ["neophyten_stmk_gesetz", "feuerbrand_wirtspflanzen_kernliste"] }
  }
}